README.rst
setup.py
yaghurl/__init__.py
yaghurl/main.py
yaghurl.egg-info/PKG-INFO
yaghurl.egg-info/SOURCES.txt
yaghurl.egg-info/dependency_links.txt
yaghurl.egg-info/entry_points.txt
yaghurl.egg-info/top_level.txt