Metadata-Version: 1.0
Name: yaghurl
Version: 0.1.dev1
Summary: Create comment links into github repositories.
Home-page: https://github.com/nejucomo/yaghurl
Author: Nathan Wilcox
Author-email: nejucomo@gmail.com
License: GPLv3
Platform: UNKNOWN
